startaker/__init__.py
startaker/jobs/__init__.py
startaker/jobs/training.py
startaker/jobs/training_x.py
startaker-0.0.9.dist-info/METADATA
startaker-0.0.9.dist-info/WHEEL
startaker-0.0.9.dist-info/top_level.txt
startaker-0.0.9.dist-info/RECORD
