Metadata-Version: 2.1
Name: startaker
Version: 0.0.9
Summary: The Cloudframe Data Science Environment
Home-page: https://github.com/cloudframe/startaker
Author: Cloudframe Analytics
Author-email: info@cloudframe.io
License: UNKNOWN
Platform: UNKNOWN
Classifier: Programming Language :: Python :: 3
Classifier: Programming Language :: Python :: 3.7
Requires-Dist: datascientist
Requires-Dist: boto3
Requires-Dist: PyYAML
